MANIFEST.in
README
README.rst
setup.py
imagestore/__init__.py
imagestore/admin.py
imagestore/apps.py
imagestore/context_processors.py
imagestore/forms.py
imagestore/test_img.jpg
imagestore/tests.py
imagestore/urls.py
imagestore/utils.py
imagestore/views.py
imagestore.egg-info/PKG-INFO
imagestore.egg-info/SOURCES.txt
imagestore.egg-info/dependency_links.txt
imagestore.egg-info/requires.txt
imagestore.egg-info/top_level.txt
imagestore/imagestore_cms/__init__.py
imagestore/imagestore_cms/cms_app.py
imagestore/imagestore_cms/cms_plugins.py
imagestore/imagestore_cms/models.py
imagestore/imagestore_cms/urls.py
imagestore/imagestore_cms/migrations/0001_initial.py
imagestore/imagestore_cms/migrations/__init__.py
imagestore/locale/fi/LC_MESSAGES/django.mo
imagestore/locale/fi/LC_MESSAGES/django.po
imagestore/locale/pt/LC_MESSAGES/django.mo
imagestore/locale/pt/LC_MESSAGES/django.po
imagestore/locale/ru/LC_MESSAGES/django.mo
imagestore/locale/ru/LC_MESSAGES/django.po
imagestore/migrations/0001_initial.py
imagestore/migrations/0002_album_brief.py
imagestore/migrations/__init__.py
imagestore/models/__init__.py
imagestore/models/album.py
imagestore/models/image.py
imagestore/models/upload.py
imagestore/models/bases/__init__.py
imagestore/models/bases/album.py
imagestore/models/bases/image.py
imagestore/static/imagestore/imagestore.css
imagestore/templates/cms/plugins/imagestore_album.html
imagestore/templates/cms/plugins/imagestore_album_carousel.html
imagestore/templates/cms/plugins/imagestore_album_carousel_base.html
imagestore/templates/imagestore/album_delete.html
imagestore/templates/imagestore/album_list.html
imagestore/templates/imagestore/base.html
imagestore/templates/imagestore/image-href.html
imagestore/templates/imagestore/image-list.html
imagestore/templates/imagestore/image-scope.html
imagestore/templates/imagestore/image.html
imagestore/templates/imagestore/image_confirm_delete.html
imagestore/templates/imagestore/image_delete.html
imagestore/templates/imagestore/image_list.html
imagestore/templates/imagestore/pagination.html
imagestore/templates/imagestore/pphoto.html
imagestore/templates/imagestore/tag-cloud.html
