Metadata-Version: 1.0
Name: imagestore
Version: 3.1.0
Summary: Gallery solution for django projects
Home-page: https://github.com/hovel/imagestore
Author: Pavel Zhukov
Author-email: gelios@gmail.com
License: GPL
Keywords: django gallery
Platform: UNKNOWN
